MANIFEST.in
README.rst
setup.py
logbook_logstash/__init__.py
logbook_logstash.egg-info/PKG-INFO
logbook_logstash.egg-info/SOURCES.txt
logbook_logstash.egg-info/dependency_links.txt
logbook_logstash.egg-info/not-zip-safe
logbook_logstash.egg-info/top_level.txt