Metadata-Version: 1.0
Name: logbook-logstash
Version: 0.1.3
Summary: JSON logstash formatter for logbook
Home-page: https://github.com/sharkerz/logbook-logstash/
Author: Darío Blanco Iturriaga
Author-email: dario@darioblanco.com
License: LICENSE
Platform: UNKNOWN
